req_update_check/__init__.py
req_update_check/ai_analyzer.py
req_update_check/auth.py
req_update_check/cache.py
req_update_check/changelog_fetcher.py
req_update_check/cli.py
req_update_check/code_scanner.py
req_update_check/core.py
req_update_check/exceptions.py
req_update_check/formatting.py
req_update_check/logging_config.py
req_update_check/prompts.py
req_update_check/ai_providers/__init__.py
req_update_check/ai_providers/base.py
req_update_check/ai_providers/claude.py
req_update_check/ai_providers/custom.py
req_update_check/ai_providers/factory.py
req_update_check/ai_providers/gemini.py
req_update_check/ai_providers/openai.py
req_update_check-0.4.2.dist-info/METADATA
req_update_check-0.4.2.dist-info/WHEEL
req_update_check-0.4.2.dist-info/entry_points.txt
req_update_check-0.4.2.dist-info/licenses/LICENSE
req_update_check-0.4.2.dist-info/RECORD
