Metadata-Version: 2.4
Name: req-update-check
Version: 0.4.2
Summary: Check Python package requirements for updates with optional AI-powered analysis
Project-URL: homepage, https://github.com/ontherivt/req-update-check
Project-URL: issues, https://github.com/ontherivt/req-update-check/issues
Author-email: PJ Hoberman <phoberman@outsideinc.com>
License-Expression: MIT
License-File: LICENSE
Requires-Python: >=3.9
Requires-Dist: requests>=2.27.0
Provides-Extra: ai
Requires-Dist: anthropic>=0.40.0; extra == 'ai'
Requires-Dist: google-generativeai>=0.8.0; extra == 'ai'
Requires-Dist: openai>=1.0.0; extra == 'ai'
Provides-Extra: all
Requires-Dist: anthropic>=0.40.0; extra == 'all'
Requires-Dist: google-generativeai>=0.8.0; extra == 'all'
Requires-Dist: openai>=1.0.0; extra == 'all'
